exploration/__init__.py
exploration/__main__.py
exploration/analysis.py
exploration/base.py
exploration/commands.py
exploration/core.py
exploration/display.py
exploration/geographic.py
exploration/graphs.py
exploration/journal.py
exploration/journal_guide.py
exploration/main.py
exploration/overview.py
exploration/parsing.py
exploration/py.typed
exploration/utils.py
exploration-0.7.5.data/scripts/egtool.py
exploration-0.7.5.dist-info/LICENSE.txt
exploration-0.7.5.dist-info/METADATA
exploration-0.7.5.dist-info/WHEEL
exploration-0.7.5.dist-info/top_level.txt
exploration-0.7.5.dist-info/RECORD
