Metadata-Version: 2.1
Name: exploration
Version: 0.7.5
Summary: Tool for reading, formatting, and manipulating exploration graphs, which are graphs (or graph-sequences) that describe exploration of a game space, principally designed with Metroidvania games in mind.
Home-page: https://cs.wellesley.edu/~pmwh/mvmap/egtool/docs/exploration
Author: Peter Mawhorter
Author-email: pmawhort@wellesley.edu
License: BSD 3-Clause License
Classifier: Programming Language :: Python :: 3 :: Only
Classifier: Development Status :: 3 - Alpha
Classifier: Intended Audience :: Developers
Classifier: Intended Audience :: Science/Research
Classifier: License :: OSI Approved :: BSD License
Classifier: Operating System :: OS Independent
Classifier: Natural Language :: English
Classifier: Topic :: Games/Entertainment
Classifier: Topic :: Scientific/Engineering :: Artificial Intelligence
Classifier: Topic :: Scientific/Engineering :: Visualization
Requires-Python: >=3.10
License-File: LICENSE.txt
Requires-Dist: networkx
Provides-Extra: test
Requires-Dist: pytest; extra == "test"
Provides-Extra: graphviz
Requires-Dist: pydot; extra == "graphviz"
